RHVoice.py
RHVoice.dll
RHVoice-0.5.1.2.dist-info/DESCRIPTION.rst
RHVoice-0.5.1.2.dist-info/METADATA
RHVoice-0.5.1.2.dist-info/RECORD
RHVoice-0.5.1.2.dist-info/WHEEL
RHVoice-0.5.1.2.dist-info/metadata.json
RHVoice-0.5.1.2.dist-info/top_level.txt
RHVoice-0.5.1.2.langdata/languages/English/accents.dt
RHVoice-0.5.1.2.langdata/languages/English/cmulex.fst,
RHVoice-0.5.1.2.langdata/languages/English/cmulex.lts,
RHVoice-0.5.1.2.langdata/languages/English/downcase.fst,
RHVoice-0.5.1.2.langdata/languages/English/gpos.fst,
RHVoice-0.5.1.2.langdata/languages/English/key.fst,
RHVoice-0.5.1.2.langdata/languages/English/labelling.xml,
RHVoice-0.5.1.2.langdata/languages/English/language.info,
RHVoice-0.5.1.2.langdata/languages/English/lseq.fst,
RHVoice-0.5.1.2.langdata/languages/English/msg.fst,
RHVoice-0.5.1.2.langdata/languages/English/numbers.fst,
RHVoice-0.5.1.2.langdata/languages/English/phonemes.xml,
RHVoice-0.5.1.2.langdata/languages/English/phrasing.dt,
RHVoice-0.5.1.2.langdata/languages/English/spell.fst,
RHVoice-0.5.1.2.langdata/languages/English/syl.fst,
RHVoice-0.5.1.2.langdata/languages/English/tok.fst,
RHVoice-0.5.1.2.langdata/languages/English/tones.dt,
RHVoice-0.5.1.2.langdata/languages/Esperanto/downcase.fst,
RHVoice-0.5.1.2.langdata/languages/Esperanto/g2p.fst,
RHVoice-0.5.1.2.langdata/languages/Esperanto/gpos.fst,
RHVoice-0.5.1.2.langdata/languages/Esperanto/key.fst,
RHVoice-0.5.1.2.langdata/languages/Esperanto/labelling.xml,
RHVoice-0.5.1.2.langdata/languages/Esperanto/language.info,
RHVoice-0.5.1.2.langdata/languages/Esperanto/msg.fst,
RHVoice-0.5.1.2.langdata/languages/Esperanto/numbers.fst,
RHVoice-0.5.1.2.langdata/languages/Esperanto/phonemes.xml,
RHVoice-0.5.1.2.langdata/languages/Esperanto/phrasing.dt,
RHVoice-0.5.1.2.langdata/languages/Esperanto/spell.fst,
RHVoice-0.5.1.2.langdata/languages/Esperanto/syl.fst,
RHVoice-0.5.1.2.langdata/languages/Esperanto/tok.fst,
RHVoice-0.5.1.2.langdata/languages/Esperanto/untranslit.fst,
RHVoice-0.5.1.2.langdata/languages/Georgian/downcase.fst,
RHVoice-0.5.1.2.langdata/languages/Georgian/g2p.fst,
RHVoice-0.5.1.2.langdata/languages/Georgian/gpos.fst,
