Metadata-Version: 2.0
Name: RHVoice
Version: 0.5.1.2
Summary: UNKNOWN
Home-page: UNKNOWN
Author: Olga Yakovleva
Author-email: yakovleva.o.v@gmail.com
License: GPL
Platform: UNKNOWN
